osint_lib/__init__.py
osint_lib/cli.py
osint_lib/osint_tracker.py
osint_lib/token_extractor.py
osint_lib/webhook_sender.py
Osint_Tool-0.2.dist-info/METADATA
Osint_Tool-0.2.dist-info/WHEEL
Osint_Tool-0.2.dist-info/entry_points.txt
Osint_Tool-0.2.dist-info/top_level.txt
Osint_Tool-0.2.dist-info/RECORD
